wu_xian_shi_xun_mylib/jm.py
wu_xian_shi_xun_mylib/lz.py
wu_xian_shi_xun_mylib/main.py
wu_xian_shi_xun_mylib/xium.py
wu_xian_shi_xun_mylib-2025.8.14.0.dist-info/METADATA
wu_xian_shi_xun_mylib-2025.8.14.0.dist-info/WHEEL
wu_xian_shi_xun_mylib-2025.8.14.0.dist-info/RECORD
