Metadata-Version: 2.4
Name: wu-xian-shi-xun-mylib
Version: 2025.8.14.0
Summary: custom browser control lib
Author-email: sodacris <wjxa20152015@gmail.com>
Requires-Python: >=3.8
Requires-Dist: cryptography
Requires-Dist: selenium
